tests/__init__.py
tests/test_activation_conv.py
tests/test_conv_padding_same.py
tests/test_maxpool_padding_same.py
tests/test_upsample.py
tests/test_view.py
torch_layers/__init__.py
torch_layers/activation_conv.py
torch_layers/conv_padding_same.py
torch_layers/maxpool_padding_same.py
torch_layers/upsample.py
torch_layers/view.py
torch_layers-0.1.2.dist-info/LICENSE
torch_layers-0.1.2.dist-info/METADATA
torch_layers-0.1.2.dist-info/WHEEL
torch_layers-0.1.2.dist-info/top_level.txt
torch_layers-0.1.2.dist-info/RECORD
