Metadata-Version: 2.1
Name: torch-layers
Version: 0.1.2
Summary: UNKNOWN
Home-page: https://github.com/justusschock/torch_layers
Author: Justus Schock
Author-email: justus.schock@rwth-aachen.de
License: BSD 2-Clause License
Requires-Dist: torch (>=1.0.0)
Requires-Dist: pytest-cov
